[{"id":"4edd86b6.331768","type":"tab","label":"FH MQTT","disabled":false,"info":"","env":[]},{"id":"e027b81483470f6e","type":"group","z":"4edd86b6.331768","name":"Set Global Mode","style":{"label":true},"nodes":["62c6f49a0d557e7c","f80c7b6e933d9c0a","2b3d5935238c0aee","8139c30e4d435db3","1e397062fcfbb0e9"],"x":774,"y":19,"w":682,"h":82},{"id":"88b8cd3b91daf3ae","type":"group","z":"4edd86b6.331768","name":"Set Mode FH","style":{"label":true},"nodes":["bd874529797813e0","845f145271bd8708","3dbb5ab41be489d2","22fcc7e745cde964","bc1904772d51db44","6626af8888151004","14ac8f4a0be280af","ad0eef5605ed22c5","67977af33b66476a"],"x":1494,"y":19,"w":552,"h":182},{"id":"b01d69bb34a09e41","type":"group","z":"4edd86b6.331768","name":"LIGHTS","style":{"label":true},"nodes":["ed876b6c.e43528","7d505bde.df4254","d0eea84c.b46138","1e4e617e.247a5f","a2adaa8d.513fa8","bfd0dbf0.b44958","1b735eb2.af9271","626ca02b.796b9","54d0eff0999dd2f8","02046d58b1fac856","b2659103b136eee6","80e36239586e7edc","b0dc3ddb928b3d38"],"x":754,"y":239,"w":1032,"h":242},{"id":"8cba373d8f4d3966","type":"group","z":"4edd86b6.331768","style":{"stroke":"#999999","stroke-opacity":"1","fill":"none","fill-opacity":"1","label":true,"label-position":"nw","color":"#a4a4a4"},"nodes":["3ab68b34.7a79d4","466ec7c3.fe6948","8386f04b.e927a","c8ca9cb76832f227","3e8ea1caee159345","e7fd9780fcb41f6a","2998be5081486cc3"],"x":154,"y":159,"w":492,"h":242},{"id":"c4cf42bd22da0e90","type":"group","z":"4edd86b6.331768","name":"Change Light State","style":{"label":true},"nodes":["29c85b88.abdbe4","647921f4d9a2d950","e540ebb37b986b6f","5361f5befcd5a5d7","8dba580b98a6ed90","d483447b72658a37","3406c60a489c0597","609827799f3da3b7","bcb4101b90fdf099","be16e854cc354bd1","68b194f85a1ef7a0","c39c0770f61b61c7","462b887551d30bf4","80b9f8ea0180e4ee","76142807ba013dd5","f77ed0a836dc3899","e7a1a9e1e22065c4"],"x":754,"y":459,"w":1272,"h":442},{"id":"ed876b6c.e43528","type":"Thing Setup","z":"4edd86b6.331768","g":"b01d69bb34a09e41","thingType":"FH_Light","things":[{"name":"Hallway","id":"21","props":{"address":2,"sv":"out_lvl_switch"},"state":[],"commands":[],"children":[]},{"name":"Office_Light","id":"5","props":{"address":6,"sv":"out_bin_switch"},"state":[],"commands":[],"children":[]},{"name":"kjøkken","id":"10","props":{"address":"3","sv":"out_lvl_switch"},"state":[],"commands":[],"children":[]},{"name":"stue","id":"11","props":{"address":"14","sv":"out_bin_switch"},"state":[],"commands":[],"children":[]},{"name":"bathroom","id":"46","props":{"address":"37","sv":"out_lvl_switch"},"state":[],"commands":[],"children":[]},{"name":"closet","id":"9","props":{"address":"12","sv":"out_bin_switch"},"state":[],"commands":[],"children":[]},{"name":"laundry","id":"15","props":{"address":9,"sv":"out_bin_switch"},"state":[],"commands":[],"children":[]},{"name":"basement","id":"17","props":{"address":"18","sv":"out_bin_switch"},"state":[],"commands":[],"children":[]},{"name":"bedroom","id":"20","props":{"address":"22","sv":"out_lvl_switch"},"state":[],"commands":[],"children":[]},{"name":"karinaoffice","id":"27","props":{"adress":"27","sv":"out_lvl_switch"},"state":[],"commands":[],"children":[]},{"name":"office","id":"26","props":{"address":"l4","sv":"out_lvl_switch"},"state":[],"commands":[],"children":[]}],"state":[{"key":"power","value":false}],"commands":[],"statusFunction":"if (state.power === undefined) return null\nlet text = state.power == \"on\" ? 'On' : 'Off'\nif (state.hasOwnProperty('brightness') && state.on){\n     text += ` ${state.brightness < 1 ? state.brightness * 100 : state.brightness}%`\n}\n   \n    \nreturn {\n    fill: state.power == \"on\" ? 'yellow' : 'grey',\n    shape: 'dot',\n    text\n}","debug":true,"x":1440,"y":280,"wires":[]},{"id":"7d505bde.df4254","type":"Thing Update","z":"4edd86b6.331768","g":"b01d69bb34a09e41","nodeName":"","name":"","thingType":"FH_Light","debug":true,"updates":[{"key":"power","type":"msg","val":"payload.val.changes.power"}],"x":1120,"y":340,"wires":[]},{"id":"d0eea84c.b46138","type":"Thing Process","z":"4edd86b6.331768","g":"b01d69bb34a09e41","nodeName":"","thingType":"FH_Light","topic":"$id","debug":false,"x":1280,"y":340,"wires":[["1b735eb2.af9271"]]},{"id":"1e4e617e.247a5f","type":"debug","z":"4edd86b6.331768","g":"b01d69bb34a09e41","name":"TO FLOWS: FH_LIght Changed ","active":false,"tosidebar":true,"console":false,"tostatus":false,"complete":"true","targetType":"full","statusVal":"","statusType":"auto","x":1430,"y":440,"wires":[]},{"id":"29c85b88.abdbe4","type":"Thing Command","z":"4edd86b6.331768","g":"c4cf42bd22da0e90","nodeName":"Set LIght","name":"","command":"","commandType":"msg","debug":false,"x":1940,"y":720,"wires":[]},{"id":"3ab68b34.7a79d4","type":"comment","z":"4edd86b6.331768","g":"8cba373d8f4d3966","name":"Futurehome MQTT communication ","info":"This example uses the Lifx platform. The Lifx node works well with the thing nodes, as it requires no initization to receive inbound messages. And the Lifx node already uses the MAC address as the message topic, so the Lifx Things are setup with the MAC address as their ID.","x":320,"y":200,"wires":[]},{"id":"faab8b45.892218","type":"Thing Setup","z":"4edd86b6.331768","thingType":"DC_Light","things":[],"state":[],"commands":[],"statusFunction":"if (state.on === undefined) return null\nlet text = state.on ? 'On' : 'Off'\nif (state.hasOwnProperty('brightness') && state.on)\n    text += ` ${state.brightness < 1 ? state.brightness * 100 : state.brightness}%`\nreturn {\n    fill: state.on ? 'yellow' : 'grey',\n    shape: 'dot',\n    text\n}","debug":false,"x":600,"y":60,"wires":[]},{"id":"a2adaa8d.513fa8","type":"change","z":"4edd86b6.331768","g":"b01d69bb34a09e41","name":"Light ID","rules":[{"t":"set","p":"topic","pt":"msg","to":"payload.val.id","tot":"msg"}],"action":"","property":"","from":"","to":"","reg":false,"x":920,"y":340,"wires":[["7d505bde.df4254"]]},{"id":"bfd0dbf0.b44958","type":"debug","z":"4edd86b6.331768","g":"b01d69bb34a09e41","name":"TO FH HUB","active":false,"tosidebar":true,"console":false,"tostatus":false,"complete":"true","targetType":"full","statusVal":"","statusType":"auto","x":1670,"y":300,"wires":[]},{"id":"1b735eb2.af9271","type":"change","z":"4edd86b6.331768","g":"b01d69bb34a09e41","name":"","rules":[{"t":"set","p":"topic","pt":"msg","to":"\"pt:j1/mt:cmd/rt:dev/rn:zw/ad:1/sv:\"& thing.props.sv & \"/ad:\"& thing.props.address & \"_0\"","tot":"jsonata"},{"t":"set","p":"payload","pt":"msg","to":"{\t    \"type\": \"cmd.binary.set\",\t    \"serv\": thing.props.sv,\t    \"val_t\": \"bool\",\t    \"val\": payload,\t    \"tags\": null,\t    \"props\": {},\t    \"ver\": \"1\",\t    \"corid\": \"\",\t    \"src\": \"node-red\",\t    \"ctime\": \"\",\t    \"uid\": \"\"\t}","tot":"jsonata"}],"action":"","property":"","from":"","to":"","reg":false,"x":1450,"y":340,"wires":[["bfd0dbf0.b44958","626ca02b.796b9"]]},{"id":"626ca02b.796b9","type":"mqtt out","z":"4edd86b6.331768","g":"b01d69bb34a09e41","name":"FH_MQTT","topic":"","qos":"","retain":"","respTopic":"","contentType":"","userProps":"","correl":"","expiry":"","broker":"41e681f.e420d8","x":1670,"y":340,"wires":[]},{"id":"466ec7c3.fe6948","type":"mqtt in","z":"4edd86b6.331768","g":"8cba373d8f4d3966","name":"FH_MQTT","topic":"pt:j1/mt:evt/rt:app/rn:vinculum/ad:1","qos":"2","datatype":"json","broker":"fa370de0.93e89","nl":false,"rap":false,"inputs":0,"x":260,"y":260,"wires":[["8386f04b.e927a","3e8ea1caee159345"]]},{"id":"8386f04b.e927a","type":"switch","z":"4edd86b6.331768","g":"8cba373d8f4d3966","name":"FH functionality","property":"payload.val.param.functionality","propertyType":"msg","rules":[{"t":"eq","v":"lighting","vt":"str"},{"t":"eq","v":"","vt":"str"}],"checkall":"false","repair":false,"outputs":2,"x":460,"y":260,"wires":[["c8ca9cb76832f227"],[]]},{"id":"54d0eff0999dd2f8","type":"debug","z":"4edd86b6.331768","g":"b01d69bb34a09e41","name":"","active":false,"tosidebar":true,"console":false,"tostatus":false,"complete":"payload.val","targetType":"msg","statusVal":"","statusType":"auto","x":940,"y":300,"wires":[]},{"id":"02046d58b1fac856","type":"Thing Trigger","z":"4edd86b6.331768","g":"b01d69bb34a09e41","nodeName":"","triggerThing":{"path":"type","type":"str","value":"FH_Light"},"triggerState":null,"triggerTest":null,"ignoreInit":false,"payload":{"type":"state","value":""},"x":950,"y":400,"wires":[["1e4e617e.247a5f","b0dc3ddb928b3d38"]]},{"id":"62c6f49a0d557e7c","type":"mqtt in","z":"4edd86b6.331768","g":"e027b81483470f6e","name":"FH_MQTT","topic":"pt:j1/mt:evt/rt:app/rn:vinculum/ad:1","qos":"0","datatype":"json","broker":"fa370de0.93e89","nl":false,"rap":false,"inputs":0,"x":860,"y":60,"wires":[["f80c7b6e933d9c0a"]]},{"id":"f80c7b6e933d9c0a","type":"switch","z":"4edd86b6.331768","g":"e027b81483470f6e","name":"","property":"payload.val.component","propertyType":"msg","rules":[{"t":"eq","v":"hub","vt":"str"}],"checkall":"true","repair":false,"outputs":1,"x":1010,"y":60,"wires":[["2b3d5935238c0aee"]]},{"id":"2b3d5935238c0aee","type":"switch","z":"4edd86b6.331768","g":"e027b81483470f6e","name":"","property":"payload.val.param.current","propertyType":"msg","rules":[{"t":"neq","v":"Mode","vt":"global"}],"checkall":"false","repair":false,"outputs":1,"x":1130,"y":60,"wires":[["8139c30e4d435db3"]]},{"id":"8139c30e4d435db3","type":"change","z":"4edd86b6.331768","g":"e027b81483470f6e","name":"","rules":[{"t":"set","p":"Mode","pt":"global","to":"payload.val.param.current","tot":"msg"}],"action":"","property":"","from":"","to":"","reg":false,"x":1280,"y":60,"wires":[["1e397062fcfbb0e9"]]},{"id":"bd874529797813e0","type":"mqtt out","z":"4edd86b6.331768","g":"88b8cd3b91daf3ae","name":"Set Mode","topic":"pt:j1/mt:cmd/rt:app/rn:vinculum/ad:1","qos":"","retain":"","respTopic":"","contentType":"","userProps":"","correl":"","expiry":"","broker":"41e681f.e420d8","x":1960,"y":100,"wires":[]},{"id":"845f145271bd8708","type":"change","z":"4edd86b6.331768","g":"88b8cd3b91daf3ae","name":"Set Mode","rules":[{"t":"set","p":"payload","pt":"msg","to":"{\t   \"ctime\": \"2019-09-04 17:36:31 +0200\",\t   \"props\": {},\t   \"resp_to\": \"pt:j1/mt:rsp/rt:app/rn:node-red/ad:flow1\",\t   \"serv\": \"vinculum\",\t   \"src\": \"node-red\",\t   \"tags\": [],\t   \"type\": \"cmd.pd7.request\",\t   \"uid\": \"09936904-8ec8-4280-9285-945d77bd0a74\",\t   \"val\": {\t       \"cmd\": \"set\",\t       \"component\": \"mode\",\t       \"id\": mode,\t       \"param\": {},\t       \"requestId\": 1\t    },\t   \"val_t\": \"object\",\t   \"ver\": \"1\"\t}","tot":"jsonata"}],"action":"","property":"","from":"","to":"","reg":false,"x":1800,"y":100,"wires":[["bd874529797813e0","67977af33b66476a"]]},{"id":"3dbb5ab41be489d2","type":"change","z":"4edd86b6.331768","g":"88b8cd3b91daf3ae","name":"away","rules":[{"t":"set","p":"mode","pt":"msg","to":"away","tot":"str"}],"action":"","property":"","from":"","to":"","reg":false,"x":1650,"y":60,"wires":[["845f145271bd8708"]]},{"id":"22fcc7e745cde964","type":"change","z":"4edd86b6.331768","g":"88b8cd3b91daf3ae","name":"home","rules":[{"t":"set","p":"mode","pt":"msg","to":"home","tot":"str"}],"action":"","property":"","from":"","to":"","reg":false,"x":1650,"y":100,"wires":[["845f145271bd8708"]]},{"id":"bc1904772d51db44","type":"change","z":"4edd86b6.331768","g":"88b8cd3b91daf3ae","name":"sleep","rules":[{"t":"set","p":"mode","pt":"msg","to":"sleep","tot":"str"}],"action":"","property":"","from":"","to":"","reg":false,"x":1650,"y":140,"wires":[["845f145271bd8708"]]},{"id":"6626af8888151004","type":"link in","z":"4edd86b6.331768","g":"88b8cd3b91daf3ae","name":"Set AWAY","links":["fc4fe81e.444628"],"x":1535,"y":60,"wires":[["3dbb5ab41be489d2"]]},{"id":"14ac8f4a0be280af","type":"link in","z":"4edd86b6.331768","g":"88b8cd3b91daf3ae","name":"Set HOME","links":["247260f.c82dca"],"x":1535,"y":100,"wires":[["22fcc7e745cde964"]]},{"id":"ad0eef5605ed22c5","type":"link in","z":"4edd86b6.331768","g":"88b8cd3b91daf3ae","name":"Set SLEEP","links":["c9b7d9c6.2c46e8"],"x":1535,"y":140,"wires":[["bc1904772d51db44"]]},{"id":"c8ca9cb76832f227","type":"link out","z":"4edd86b6.331768","g":"8cba373d8f4d3966","name":"FH_Lights","mode":"link","links":["b2659103b136eee6"],"x":595,"y":260,"wires":[]},{"id":"b2659103b136eee6","type":"link in","z":"4edd86b6.331768","g":"b01d69bb34a09e41","name":"FH_Lights","links":["c8ca9cb76832f227"],"x":795,"y":320,"wires":[["a2adaa8d.513fa8","54d0eff0999dd2f8"]]},{"id":"1e397062fcfbb0e9","type":"link out","z":"4edd86b6.331768","g":"e027b81483470f6e","name":"FH_Mode_Set","mode":"link","links":["8456ad2c.7b492"],"x":1415,"y":60,"wires":[]},{"id":"647921f4d9a2d950","type":"Thing Get","z":"4edd86b6.331768","g":"c4cf42bd22da0e90","nodeName":"Get Ligth Status","name":"","props":[{"msgProp":"payload","thingProp":"state","path":"power"}],"x":1400,"y":720,"wires":[["f77ed0a836dc3899","e7a1a9e1e22065c4"]]},{"id":"e540ebb37b986b6f","type":"change","z":"4edd86b6.331768","g":"c4cf42bd22da0e90","name":"Set State","rules":[{"t":"change","p":"payload","pt":"msg","from":"on","fromt":"str","to":"false","tot":"bool"},{"t":"change","p":"payload","pt":"msg","from":"off","fromt":"str","to":"true","tot":"bool"}],"action":"","property":"","from":"","to":"","reg":false,"x":1780,"y":720,"wires":[["29c85b88.abdbe4"]]},{"id":"5361f5befcd5a5d7","type":"change","z":"4edd86b6.331768","g":"c4cf42bd22da0e90","name":"Office_Light","rules":[{"t":"set","p":"topic","pt":"msg","to":"Office_Light","tot":"str"}],"action":"","property":"","from":"","to":"","reg":false,"x":1130,"y":820,"wires":[["647921f4d9a2d950"]]},{"id":"8dba580b98a6ed90","type":"change","z":"4edd86b6.331768","g":"c4cf42bd22da0e90","name":"Hallway","rules":[{"t":"set","p":"topic","pt":"msg","to":"Hallway","tot":"str"}],"action":"","property":"","from":"","to":"","reg":false,"x":1140,"y":620,"wires":[["647921f4d9a2d950"]]},{"id":"d483447b72658a37","type":"change","z":"4edd86b6.331768","g":"c4cf42bd22da0e90","name":"kjøkken","rules":[{"t":"set","p":"topic","pt":"msg","to":"kjøkken","tot":"str"}],"action":"","property":"","from":"","to":"","reg":false,"x":1140,"y":580,"wires":[["647921f4d9a2d950"]]},{"id":"3406c60a489c0597","type":"change","z":"4edd86b6.331768","g":"c4cf42bd22da0e90","name":"stue","rules":[{"t":"set","p":"topic","pt":"msg","to":"stue","tot":"str"}],"action":"","property":"","from":"","to":"","reg":false,"x":1150,"y":540,"wires":[["647921f4d9a2d950"]]},{"id":"609827799f3da3b7","type":"change","z":"4edd86b6.331768","g":"c4cf42bd22da0e90","name":"bathroom","rules":[{"t":"set","p":"topic","pt":"msg","to":"bathroom","tot":"str"}],"action":"","property":"","from":"","to":"","reg":false,"x":1140,"y":700,"wires":[["647921f4d9a2d950"]]},{"id":"bcb4101b90fdf099","type":"change","z":"4edd86b6.331768","g":"c4cf42bd22da0e90","name":"closet","rules":[{"t":"set","p":"topic","pt":"msg","to":"closet","tot":"str"}],"action":"","property":"","from":"","to":"","reg":false,"x":1150,"y":500,"wires":[["647921f4d9a2d950"]]},{"id":"be16e854cc354bd1","type":"change","z":"4edd86b6.331768","g":"c4cf42bd22da0e90","name":"laundry","rules":[{"t":"set","p":"topic","pt":"msg","to":"laundry","tot":"str"}],"action":"","property":"","from":"","to":"","reg":false,"x":1140,"y":780,"wires":[["647921f4d9a2d950"]]},{"id":"68b194f85a1ef7a0","type":"change","z":"4edd86b6.331768","g":"c4cf42bd22da0e90","name":"basement","rules":[{"t":"set","p":"topic","pt":"msg","to":"basement","tot":"str"}],"action":"","property":"","from":"","to":"","reg":false,"x":1140,"y":740,"wires":[["647921f4d9a2d950"]]},{"id":"c39c0770f61b61c7","type":"change","z":"4edd86b6.331768","g":"c4cf42bd22da0e90","name":"bedroom","rules":[{"t":"set","p":"topic","pt":"msg","to":"bedroom","tot":"str"}],"action":"","property":"","from":"","to":"","reg":false,"x":1140,"y":660,"wires":[["647921f4d9a2d950"]]},{"id":"462b887551d30bf4","type":"change","z":"4edd86b6.331768","g":"c4cf42bd22da0e90","name":"karinaoffice","rules":[{"t":"set","p":"topic","pt":"msg","to":"karinaoffice","tot":"str"}],"action":"","property":"","from":"","to":"","reg":false,"x":1130,"y":860,"wires":[["647921f4d9a2d950"]]},{"id":"80b9f8ea0180e4ee","type":"link in","z":"4edd86b6.331768","g":"c4cf42bd22da0e90","name":"Set_Lights","links":["c2a6540cf2006146","d3afa1ea39895105"],"x":795,"y":660,"wires":[["76142807ba013dd5"]]},{"id":"76142807ba013dd5","type":"switch","z":"4edd86b6.331768","g":"c4cf42bd22da0e90","name":"","property":"topic","propertyType":"msg","rules":[{"t":"eq","v":"Closet","vt":"str"},{"t":"eq","v":"KJØKKEN","vt":"str"},{"t":"eq","v":"G-LYS","vt":"str"},{"t":"eq","v":"S-LYS","vt":"str"},{"t":"eq","v":"BA-LYS","vt":"str"},{"t":"eq","v":"K-LYS","vt":"str"},{"t":"eq","v":"vaskerom","vt":"str"},{"t":"eq","v":"O-LYS","vt":"str"},{"t":"eq","v":"K-O-LYS","vt":"str"}],"checkall":"true","repair":false,"outputs":9,"x":910,"y":660,"wires":[["bcb4101b90fdf099"],["d483447b72658a37","3406c60a489c0597"],["8dba580b98a6ed90"],["c39c0770f61b61c7"],["609827799f3da3b7"],["68b194f85a1ef7a0"],["be16e854cc354bd1"],["5361f5befcd5a5d7"],["462b887551d30bf4"]]},{"id":"80e36239586e7edc","type":"link out","z":"4edd86b6.331768","g":"b01d69bb34a09e41","name":"Light_Changed","mode":"link","links":["d8c7329f354642ba","ee3e825fcad82993"],"x":1555,"y":400,"wires":[]},{"id":"b0dc3ddb928b3d38","type":"delay","z":"4edd86b6.331768","g":"b01d69bb34a09e41","name":"","pauseType":"timed","timeout":"5","timeoutUnits":"seconds","rate":"1","nbRateUnits":"2","rateUnits":"second","randomFirst":"1","randomLast":"5","randomUnits":"seconds","drop":true,"allowrate":false,"outputs":1,"x":1190,"y":400,"wires":[["80e36239586e7edc"]]},{"id":"f77ed0a836dc3899","type":"debug","z":"4edd86b6.331768","g":"c4cf42bd22da0e90","name":"","active":false,"tosidebar":true,"console":false,"tostatus":false,"complete":"true","targetType":"full","statusVal":"","statusType":"auto","x":1540,"y":640,"wires":[]},{"id":"e7a1a9e1e22065c4","type":"switch","z":"4edd86b6.331768","g":"c4cf42bd22da0e90","name":"","property":"movement","propertyType":"msg","rules":[{"t":"neq","v":"payload","vt":"msg"}],"checkall":"true","repair":false,"outputs":1,"x":1580,"y":720,"wires":[["e540ebb37b986b6f"]]},{"id":"3e8ea1caee159345","type":"switch","z":"4edd86b6.331768","g":"8cba373d8f4d3966","name":"External FH ( HUE)","property":"payload.val.param.type.subtype","propertyType":"msg","rules":[{"t":"eq","v":"presence","vt":"str"}],"checkall":"true","repair":false,"outputs":1,"x":460,"y":320,"wires":[["e7fd9780fcb41f6a"]]},{"id":"e7fd9780fcb41f6a","type":"change","z":"4edd86b6.331768","g":"8cba373d8f4d3966","name":"","rules":[{"t":"set","p":"payload","pt":"msg","to":"payload.val.param.param.presence","tot":"msg"}],"action":"","property":"","from":"","to":"","reg":false,"x":480,"y":360,"wires":[["2998be5081486cc3"]]},{"id":"2998be5081486cc3","type":"link out","z":"4edd86b6.331768","g":"8cba373d8f4d3966","name":"HUE PRESENCE","mode":"link","links":["885fc820467d8739"],"x":605,"y":360,"wires":[]},{"id":"67977af33b66476a","type":"link out","z":"4edd86b6.331768","g":"88b8cd3b91daf3ae","name":"","mode":"link","links":["469534ab7d1a6e67"],"x":1885,"y":160,"wires":[]},{"id":"41e681f.e420d8","type":"mqtt-broker","name":"FutureHomeHub","broker":"cube.local","port":"1884","clientid":"","usetls":false,"compatmode":false,"keepalive":"60","cleansession":true,"birthTopic":"","birthQos":"0","birthPayload":"","closeTopic":"","closeQos":"0","closePayload":"","willTopic":"","willQos":"0","willPayload":""},{"id":"fa370de0.93e89","type":"mqtt-broker","name":"Smarthub","broker":"cube.local","port":"1884","clientid":"","usetls":false,"protocolVersion":"4","keepalive":"60","cleansession":true,"birthTopic":"","birthQos":"0","birthPayload":"","birthMsg":{},"closeTopic":"","closeQos":"0","closePayload":"","closeMsg":{},"willTopic":"","willQos":"0","willPayload":"","willMsg":{},"sessionExpiry":""}]